flare/__init__.py
flare/__main__.py
flare/flare.py
flare/virtualizer.py
flare-0.0.8.dist-info/DESCRIPTION.rst
flare-0.0.8.dist-info/METADATA
flare-0.0.8.dist-info/RECORD
flare-0.0.8.dist-info/WHEEL
flare-0.0.8.dist-info/entry_points.txt
flare-0.0.8.dist-info/metadata.json
flare-0.0.8.dist-info/top_level.txt
