Metadata-Version: 2.0
Name: flare
Version: 0.0.8
Summary: Data Science Project Builder.
Home-page: http://github.com/francisbautista/flare
Author: Francis Bautista
Author-email: francis.bautista07@gmail.com
License: UNKNOWN
Platform: UNKNOWN
Requires-Dist: argparse
